./.env.example
./.gitignore
./.python-version
./PKG-INFO
./README.md
./conftest.py
./main.py
./pyproject.toml
./requirements.txt
./setup.py
./uv.lock
./rabbitmv_mcp/__init__.py
./rabbitmv_mcp/config.py
./tests/test_mcp_service.py
rabbitmv_mcp-0.1.2.dist-info/METADATA
rabbitmv_mcp-0.1.2.dist-info/WHEEL
rabbitmv_mcp-0.1.2.dist-info/entry_points.txt
rabbitmv_mcp-0.1.2.dist-info/RECORD
