Metadata-Version: 2.4
Name: rabbitmv-mcp
Version: 0.1.2
Summary: RabbitMV MCP Service - A Model Context Protocol implementation for media data services
Project-URL: Homepage, https://github.com/rabbitmv/rabbitmv-mcp
Project-URL: Repository, https://github.com/rabbitmv/rabbitmv-mcp.git
Project-URL: Issues, https://github.com/rabbitmv/rabbitmv-mcp/issues
Author-email: RabbitMV Team <team@rabbitmv.com>
License: MIT
Keywords: mcp,media,service,video
Classifier: Development Status :: 4 - Beta
Classifier: Intended Audience :: Developers
Classifier: License :: OSI Approved :: MIT License
Classifier: Programming Language :: Python :: 3.12
Classifier: Topic :: Multimedia :: Video
Classifier: Topic :: Software Development :: Libraries :: Python Modules
Requires-Python: >=3.12
Requires-Dist: httpx>=0.24.0
Requires-Dist: mcp[cli]>=0.1.0
Requires-Dist: orjson>=3.9.0
Requires-Dist: pydantic>=2.5.0
Requires-Dist: python-dotenv>=1.0.0
Requires-Dist: uvloop>=0.19.0; sys_platform != 'win32'
Provides-Extra: dev
Requires-Dist: black>=23.9.0; extra == 'dev'
Requires-Dist: isort>=5.12.0; extra == 'dev'
Requires-Dist: mypy>=1.5.0; extra == 'dev'
Requires-Dist: pytest-asyncio>=0.21.0; extra == 'dev'
Requires-Dist: pytest-cov>=4.1.0; extra == 'dev'
Requires-Dist: pytest>=7.4.0; extra == 'dev'
